{
  "channel_name": "the_hindu",
  "conversation_id": "1919046492330836037",
  "url": "https://x.com/the_hindu/status/1919046492330836037",
  "total_comments": 236,
  "scrape_start_time": "2025-09-16 03:29:48",
  "comments": [
    {
      "text": "Grok verified the facts.",
      "timestamp": "2025-09-16 03:20:13"
    },
    {
      "text": "It isn't just \"cultural pride.\"\nIt is abuse of ancient knowledge to promote present-day political career..",
      "timestamp": "2025-09-16 03:20:13"
    },
    {
      "text": "She’s got her head in the clouds…NASA needs to send a satellite to investigate the grey matter!!",
      "timestamp": "2025-09-16 03:20:13"
    },
    {
      "text": "This rumor likely stems from a 1985 paper by NASA researcher Rick Briggs, who explored how Sanskrit’s grammatical structure could be relevant for knowledge representation in AI. However, NASA has never officially endorsed Sanskrit for AI or communication.",
      "timestamp": "2025-09-16 03:20:13"
    },
    {
      "text": "What a fall for The Hindu",
      "timestamp": "2025-09-16 03:20:13"
    },
    {
      "text": "@gupta_rekha\n oye madam concentrate on your job.\nLeave science for the scientists.\n\nBJP ministers are a bunch of clowns jumping around in the circus they call governance.",
      "timestamp": "2025-09-16 03:20:13"
    },
    {
      "text": "Desh bahut galat haaton mai.\n\nKabhi kabhi sonchta hoon gabbar sing banjaou.\n\nNa rahenge haat ,na mulk tabah hoga.",
      "timestamp": "2025-09-16 03:20:13"
    },
    {
      "text": "What a fall Delhi from Sheila Dixit toh this",
      "timestamp": "2025-09-16 03:20:13"
    },
    {
      "text": "Hindus take your jhun jhuna ",
      "timestamp": "2025-09-16 03:20:13"
    },
    {
      "text": "Breaking: NASA scientists caught speaking in fluent Sanskrit while launching rockets from Chandni Chowk. Delhiites, better brush up on your Vedas — interstellar WiFi only works in pure Shuddh Sanskrit now!",
      "timestamp": "2025-09-16 03:20:13"
    },
    {
      "text": "That’s the IQ required to be selected for a leadership post in sangh ecosystem. Bad luck Delhi.",
      "timestamp": "2025-09-16 03:20:13"
    },
    {
      "text": "Except for one paper by Rick Briggs in 1985 (distantly associated with NASA) no other research is done nor officially claimed by NASA. It's more a WA claim",
      "timestamp": "2025-09-16 03:20:13"
    },
    {
      "text": "इस वाट्सएपिया मेरिट(GC merit) वालो को NASA  का फुलफॉर्म भी नहीं पता होगा लेकिन मेरिट उफान मारता है।\n@grok\n NASA primarily focuses on aerospace, planetary science, astrophysics, and space technology development. It is not a language research organization.",
      "timestamp": "2025-09-16 03:20:13"
    },
    {
      "text": "Why are all chamans occupying high positions?",
      "timestamp": "2025-09-16 03:20:13"
    },
    {
      "text": "Dear lord. Delhi is now led by the unlettered",
      "timestamp": "2025-09-16 03:20:13"
    },
    {
      "text": "Not sure about NASA but these guys will definitely take us back in time when Sanskrit was  spoken widely and when Pushpak vimanas were in everyone’s backyard.",
      "timestamp": "2025-09-16 03:20:13"
    },
    {
      "text": "I don't know about NASA but sanskrit grammar system of panini most advanced, like algorithm of computer programming",
      "timestamp": "2025-09-16 03:20:13"
    },
    {
      "text": "Please Fix the Headline. You're The Hindu, not WhatsApp University. You're supposed to analyze, not just echo what every politician says. It's your job to fact-check and to call out the liar Otherwise, how are you different from a loudspeaker?",
      "timestamp": "2025-09-16 03:20:13"
    },
    {
      "text": "@grok\n how many people in the world know Sanskrit today?",
      "timestamp": "2025-09-16 03:20:13"
    },
    {
      "text": "@grok\n  Statement of Delhi CM is true? Write in 10 words",
      "timestamp": "2025-09-16 03:20:13"
    },
    {
      "text": "Better for Rekha  to consult a psychiatrist immediately for her serious mental issues. Speaking like Yogi.",
      "timestamp": "2025-09-16 03:20:13"
    },
    {
      "text": "Straight from WhatsApp forward.",
      "timestamp": "2025-09-16 03:20:13"
    },
    {
      "text": "Pata Nahi Ji Konsa NASA Karta Hain",
      "timestamp": "2025-09-16 03:20:13"
    },
    {
      "text": "she enjoys making joke out of herself.\n\nTypical Bjp.",
      "timestamp": "2025-09-16 03:20:44"
    },
    {
      "text": "तभी कहते हैं इन अनपढ़ चूतिये गँवारों को कोई भी ऐसी post नहीं देनी चाहिए! \nऔर नारंगी भक्तों को केवल ये चूतिये लोग ही पसंद आते हैं! ",
      "timestamp": "2025-09-16 03:20:44"
    },
    {
      "text": "Sanskrit scientific language, NASA has written papers on it: Delhi CM Rekha Gupta\nthehindu.com/news/cities/De\n…",
      "timestamp": "2025-09-16 03:20:44"
    },
    {
      "text": "उसको बोलो...संस्कृत जिसको पडना है वो पड़ ही रहा hai पिछले कई वर्षों से...तुमको जिस काम के लिए भेजा है वो करो...सड़क बिजली शिक्षा और चिकित्सा पर काम करो और अपने PAW PAW के तरह फालतू की और इधर उधर की बात मत करो",
      "timestamp": "2025-09-16 03:20:44"
    },
    {
      "text": "They gotta stop drinking cow urine",
      "timestamp": "2025-09-16 03:20:44"
    },
    {
      "text": "It indeed is Netriji \n@BJP4Delhi\n CMji \n@gupta_rekha\n. Does ur \n@BJP4India\n &/or its Guru \n@RSSorg\n teach Sanskrit to all its members/Swayam Sevaks or just hail Sanskrit? U & ur/BJP Big Boss Masters of Entire Sanskrit?",
      "timestamp": "2025-09-16 03:20:44"
    },
    {
      "text": "She can't read so I don't where how she knows!",
      "timestamp": "2025-09-16 03:20:44"
    },
    {
      "text": "WhatsApp graduate",
      "timestamp": "2025-09-16 03:20:44"
    },
    {
      "text": "Do NASA know this ?",
      "timestamp": "2025-09-16 03:20:44"
    },
    {
      "text": "Pajeets exposed  ",
      "timestamp": "2025-09-16 03:20:44"
    },
    {
      "text": "Sanskrit plays a vital role in various academic fields, including Indo-European studies, and is a subject of study in numerous universities globally. \n\nHowever, it's essential to clarify that labeling it a 'scientific language' used by NASA is inaccurate and misleading.",
      "timestamp": "2025-09-16 03:20:44"
    },
    {
      "text": "ku india ki bejjati krte ho? ISRO ke baare mein kya sochenge videshi?",
      "timestamp": "2025-09-16 03:20:44"
    },
    {
      "text": "@grok\n Did NASA write any paper on Sanskrit?",
      "timestamp": "2025-09-16 03:20:44"
    },
    {
      "text": "Ok. The point is how many inventions Rekha Gupta or her ancestors done using Sanskrit. The answer is another overhyped invention of India.",
      "timestamp": "2025-09-16 03:20:44"
    },
    {
      "text": "matalab bramha ne sanskrit me sarswati ko pla tha ",
      "timestamp": "2025-09-16 03:20:44"
    },
    {
      "text": "India is doomed with these kinda leaders. Sanghis this is on you.",
      "timestamp": "2025-09-16 03:20:44"
    },
    {
      "text": "Caught in there own Whatsapp propaganda.",
      "timestamp": "2025-09-16 03:20:44"
    },
    {
      "text": "Official WhatsApp graduate CM of India",
      "timestamp": "2025-09-16 03:20:44"
    },
    {
      "text": "Bad time for India because of these foolish dumps",
      "timestamp": "2025-09-16 03:20:44"
    },
    {
      "text": "@narendramodi\n मोदी जी का सपना पूरा हो रहा है, जितने बीजेपी \n@BJP4India\n   के मुख्यमन्त्री हैं, सब उनके अपने जैसे appoint हो रहे हैं.",
      "timestamp": "2025-09-16 03:20:45"
    },
    {
      "text": "The irony is one has to still rely on a foreign institution for credibility  while we go digging ",
      "timestamp": "2025-09-16 03:20:45"
    },
    {
      "text": "Lie\nSimply big lie\nFrom Book called \nBunch of Lies",
      "timestamp": "2025-09-16 03:20:45"
    },
    {
      "text": "Almost 25 years ago, #Sanskrit was promoted as the language most suited for #computers.\n#Swaraj spoke of it profusely and #Bachan clapped with pride, along with a hall full of people.\nWonder what's the status today? ",
      "timestamp": "2025-09-16 03:20:45"
    },
    {
      "text": "Yes. All scientific research in the world is because of Sanskrit. That is why nobody in India except some poojaris know it.",
      "timestamp": "2025-09-16 03:20:45"
    },
    {
      "text": "Don't publish whatsapp university news.",
      "timestamp": "2025-09-16 03:20:45"
    },
    {
      "text": "Sakha student.",
      "timestamp": "2025-09-16 03:20:45"
    },
    {
      "text": "WhatsApp University aunty in the BJ Party. Nothing surprising here... Move on.",
      "timestamp": "2025-09-16 03:20:45"
    },
    {
      "text": "Really? Does NASA even know about this claim?",
      "timestamp": "2025-09-16 03:20:45"
    },
    {
      "text": "There was one paper written by Rick Briggs in 1985. None since then. The subject was the possibility to use Sanskrit in AI due to its rule based structure. Not papers, one paper only.",
      "timestamp": "2025-09-16 03:20:45"
    },
    {
      "text": "Congratulations Delhi...this is what you have elected ",
      "timestamp": "2025-09-16 03:20:45"
    },
    {
      "text": "Sanskrit is an Indo-Europan  language! .Latin and Greek are also part of the family. Nothing special about it.",
      "timestamp": "2025-09-16 03:20:45"
    },
    {
      "text": "If Sanskrit is a scientific language then it must be promoted within ISRO and not just NASA.",
      "timestamp": "2025-09-16 03:21:16"
    },
    {
      "text": "@NASA\n @TheOnion\n @grok\n is this true?",
      "timestamp": "2025-09-16 03:21:16"
    },
    {
      "text": "@AskPerplexity\n @grok\n can you fact check the claim?",
      "timestamp": "2025-09-16 03:21:16"
    },
    {
      "text": "@grok\n Please elaborate on how Panini Sanskrit grammar's has influenced on development of Panini-Backus Naur Form for Computer Language grammar, Finate state automaton, lambda calculus, and how Sanskrit's generative grammar can help in information preservation and AI for future",
      "timestamp": "2025-09-16 03:21:16"
    },
    {
      "text": "Fools can say anything ....there is no limit for stupidity.",
      "timestamp": "2025-09-16 03:21:16"
    },
    {
      "text": "Perfect BJP candidate.",
      "timestamp": "2025-09-16 03:21:16"
    },
    {
      "text": "Even NASA didn't know this whatsapp university \"fact\".",
      "timestamp": "2025-09-16 03:21:16"
    },
    {
      "text": "Hey \n@NASA\n our politician \n@gupta_rekha\n knows something you don't.",
      "timestamp": "2025-09-16 03:21:16"
    },
    {
      "text": "Why didn't Modi Government convert it into a programming language in 11 years?",
      "timestamp": "2025-09-16 03:21:16"
    },
    {
      "text": "Hahahaha…",
      "timestamp": "2025-09-16 03:21:16"
    },
    {
      "text": "From IIT graduate CM to this WhatsApp graduate CM",
      "timestamp": "2025-09-16 03:21:16"
    },
    {
      "text": "She's high on gomutr",
      "timestamp": "2025-09-16 03:21:16"
    },
    {
      "text": "Did she forget to get a phd in linguistic \nOr did she declare she already has one from DU",
      "timestamp": "2025-09-16 03:21:16"
    },
    {
      "text": "Kuch kaam ki baat karein..?",
      "timestamp": "2025-09-16 03:21:16"
    },
    {
      "text": "CM of the capital state!",
      "timestamp": "2025-09-16 03:21:16"
    },
    {
      "text": ",",
      "timestamp": "2025-09-16 03:21:16"
    },
    {
      "text": "Behenji ko kaise pata?!? Inko kaunsa English aati hai? Ya NASA gayi hain? Ainve phatte maaro !!",
      "timestamp": "2025-09-16 03:21:16"
    },
    {
      "text": "She had a nice dream",
      "timestamp": "2025-09-16 03:21:16"
    },
    {
      "text": "Why don’t we teach this scientific language in all schools in the country, then?\nAt least science the subjects ?",
      "timestamp": "2025-09-16 03:21:16"
    },
    {
      "text": "Three cheers for \n@gupta_rekha\n the WhatsApp university graduate",
      "timestamp": "2025-09-16 03:21:16"
    },
    {
      "text": "Pretty much irrelevant now.",
      "timestamp": "2025-09-16 03:21:16"
    },
    {
      "text": "Fuck sake",
      "timestamp": "2025-09-16 03:21:16"
    },
    {
      "text": "All bjpee cms come from the same syllables appointed by Paw paw n Tadipaar",
      "timestamp": "2025-09-16 03:21:16"
    },
    {
      "text": "Can she read Sanskrit?",
      "timestamp": "2025-09-16 03:21:16"
    },
    {
      "text": "Delhi's CM is a WhatsApp Forward ",
      "timestamp": "2025-09-16 03:21:16"
    },
    {
      "text": "Education matters",
      "timestamp": "2025-09-16 03:21:16"
    },
    {
      "text": "Ye wattsapp ki University se password ajj kal CM bhi bun rahe hein",
      "timestamp": "2025-09-16 03:21:16"
    },
    {
      "text": "hey, as a newspaper and practitioner of journalism, were you able to verify this claim and include some information?",
      "timestamp": "2025-09-16 03:21:16"
    },
    {
      "text": "Yogi is exporting Gobar or Cow dung  paint to USA  UAE, Australia, Switzerland, Singapore, Indonesia, Italy. ",
      "timestamp": "2025-09-16 03:21:47"
    },
    {
      "text": "Aanpad lady..shame on delhi to vote ofr such thugs vs IItian",
      "timestamp": "2025-09-16 03:21:47"
    },
    {
      "text": "Agar AAP apna ego todke congress ke saath coalition bana leti toh dilli ka itna ganda downfall dekhne ko na milta",
      "timestamp": "2025-09-16 03:21:47"
    },
    {
      "text": "May be aunty what's up graduate from rsss fake news spread university..",
      "timestamp": "2025-09-16 03:21:47"
    },
    {
      "text": "What a misfortune of Indian people that they are being ruled by these buffoons!",
      "timestamp": "2025-09-16 03:21:47"
    },
    {
      "text": "Lol whatsapp forward",
      "timestamp": "2025-09-16 03:21:47"
    },
    {
      "text": "If Sanskrit is indeed a scientific language, it doesn't need Nasa certification.",
      "timestamp": "2025-09-16 03:21:47"
    },
    {
      "text": "Sad we have such uninformed n illiterate leaders",
      "timestamp": "2025-09-16 03:21:47"
    },
    {
      "text": "Ha ha ha",
      "timestamp": "2025-09-16 03:21:47"
    },
    {
      "text": "Went from an IIT CM to this  fucking hell Delhi, whyyyyy  ",
      "timestamp": "2025-09-16 03:21:47"
    },
    {
      "text": "Bro Source\nWhatsApp university ",
      "timestamp": "2025-09-16 03:21:47"
    },
    {
      "text": "Itna “scientific” hai k age hi nehi bar paya!",
      "timestamp": "2025-09-16 03:21:47"
    },
    {
      "text": "When?",
      "timestamp": "2025-09-16 03:21:47"
    },
    {
      "text": "Bullshit ",
      "timestamp": "2025-09-16 03:21:47"
    },
    {
      "text": "Wonder why \n@isro\n hasn't switched to sanskrit?",
      "timestamp": "2025-09-16 03:21:47"
    },
    {
      "text": "If we ask for any evidence they will book you under UAPA!",
      "timestamp": "2025-09-16 03:21:47"
    },
    {
      "text": "I am a research scholar, I want to read such papers",
      "timestamp": "2025-09-16 03:21:47"
    },
    {
      "text": "All sanghis are in same whatsapp group ",
      "timestamp": "2025-09-16 03:21:47"
    },
    {
      "text": "Congratulations Delhi",
      "timestamp": "2025-09-16 03:21:47"
    },
    {
      "text": "This is what happens when a WhatsApp university Aunty became CM of Delhi ",
      "timestamp": "2025-09-16 03:21:47"
    },
    {
      "text": "Ye Kab ho gaya??\nWhagsapp University please share details!!",
      "timestamp": "2025-09-16 03:21:47"
    },
    {
      "text": "First of all why does a news such as these in the newspaper making useless readings",
      "timestamp": "2025-09-16 03:21:47"
    },
    {
      "text": "वॉट्सएप वाली",
      "timestamp": "2025-09-16 03:21:47"
    },
    {
      "text": "देश को अनपढ़ नेताओं से खतरा नहीं है\nपढ़ें लिखे नेताओं से खतरा है",
      "timestamp": "2025-09-16 03:21:47"
    },
    {
      "text": "Why would english speaking people want the head ache of reading sanskrit.  New coaching institute will spring up to scam poor middle class family",
      "timestamp": "2025-09-16 03:21:47"
    },
    {
      "text": "Sanskrit originates from Syria, not India and NASA did no such thing.",
      "timestamp": "2025-09-16 03:22:18"
    },
    {
      "text": "lets use #Sanskrit as our national language .",
      "timestamp": "2025-09-16 03:22:18"
    },
    {
      "text": "Rekha Gupta का गोबर whatsapp university gyaanchodi ko ticket लगाकर स्टूडियो या पॉडकास्ट में रखो ",
      "timestamp": "2025-09-16 03:22:18"
    },
    {
      "text": "Only when people are ready to believe anything, the ones fooling them look like heroes. Forget NASA papers—just add a fancy twist to local nonsense and it sells..Why promote an expired language? .",
      "timestamp": "2025-09-16 03:22:18"
    },
    {
      "text": "Fake like the degree ?",
      "timestamp": "2025-09-16 03:22:18"
    },
    {
      "text": "Whatsapp University forwarded!?",
      "timestamp": "2025-09-16 03:22:18"
    },
    {
      "text": "If Sanskrit is so advanced that NASA studies it, I assume Chandrayaan-4 will be chanting mantras instead of using fuel.",
      "timestamp": "2025-09-16 03:22:18"
    },
    {
      "text": "Hai La \nYeh toh state secrets khule aam bata rahi hai - Tauba Tauba",
      "timestamp": "2025-09-16 03:22:18"
    },
    {
      "text": "If a thief doesn't reform even after being caught, theft can never be eradicated.",
      "timestamp": "2025-09-16 03:22:18"
    },
    {
      "text": "Only Sanskrit talk & use in NASA",
      "timestamp": "2025-09-16 03:22:18"
    },
    {
      "text": "can these mindsets make india VIKSIT BHARAT? \nthis is unfortunate of India's politics...\nilliterates are rulers",
      "timestamp": "2025-09-16 03:22:18"
    },
    {
      "text": "यह है इनकी मेरीट",
      "timestamp": "2025-09-16 03:22:18"
    },
    {
      "text": "What can we expect from WhatsApp graduates",
      "timestamp": "2025-09-16 03:22:18"
    },
    {
      "text": "Show me the paper",
      "timestamp": "2025-09-16 03:22:18"
    },
    {
      "text": "IITian CM to WhatsApp university CM.. \n\nWhat a fall for Delhi",
      "timestamp": "2025-09-16 03:22:18"
    },
    {
      "text": "This shit is still selling in our damed country",
      "timestamp": "2025-09-16 03:22:18"
    },
    {
      "text": "An example of obvious coordination with Phonology Semantics and Graphics : if ऋण then तरङ्ग where we can specify रङ्ग and conclude with राग. However, we can continue to reflect on this proposal...",
      "timestamp": "2025-09-16 03:22:18"
    },
    {
      "text": "And what problems have we solved using that scientific knowledge?",
      "timestamp": "2025-09-16 03:22:18"
    },
    {
      "text": "And she was the co-author!!",
      "timestamp": "2025-09-16 03:22:18"
    },
    {
      "text": "तो बोलो, ये बात हिंदी में क्यों कही जा रही है?",
      "timestamp": "2025-09-16 03:22:18"
    },
    {
      "text": "@NASA\n can you please give clarity on this.",
      "timestamp": "2025-09-16 03:22:18"
    },
    {
      "text": "WhatsApp forward pad rahi hain",
      "timestamp": "2025-09-16 03:22:18"
    },
    {
      "text": "My main question is what makes a language scientific? Like literally,  im so confused rn. Please any sanatani dharma hindu enlighten me. What a language scientific and makes the other not. Scientific language is a new discovery in its own essence",
      "timestamp": "2025-09-16 03:22:18"
    },
    {
      "text": "PULWAMMA was done by Pakistan? Have a heart? I they did that then all security forces, CHIEF OF ALL DEFENCES FORCES,NSA DOVA( SO CALLED JAMES BOND),HM AMIT SHAH, DO CALLED FUCKEN CHANKYEA? Should have died in shame?  But bastards have no shame?",
      "timestamp": "2025-09-16 03:22:18"
    },
    {
      "text": "Is there any way to penalize leaders who spread misinformation",
      "timestamp": "2025-09-16 03:22:18"
    },
    {
      "text": "Has someone told NASA about it?",
      "timestamp": "2025-09-16 03:22:18"
    },
    {
      "text": "Delhi is blessed to have you …",
      "timestamp": "2025-09-16 03:22:18"
    },
    {
      "text": "When BJPigs are in power… dooms day is just around the corner!",
      "timestamp": "2025-09-16 03:22:18"
    },
    {
      "text": "yes she was that NASA scientist who wrote that paper and now shifted back to India for stating this fact before all Indians.",
      "timestamp": "2025-09-16 03:22:18"
    },
    {
      "text": "Unpadh jahil gawaar politician",
      "timestamp": "2025-09-16 03:22:18"
    },
    {
      "text": "Not true. I don’t know where she got this information. Absolutely BS.",
      "timestamp": "2025-09-16 03:22:18"
    },
    {
      "text": "From IIT CM to a WhatsApp-educated CM -- wah, nice job Delhi voters!",
      "timestamp": "2025-09-16 03:22:49"
    },
    {
      "text": "Hey \n@NASA\n I know you got important stuff, but can you spare a thought for the uninformed and confirm if you really have started coding in Sanskrit?",
      "timestamp": "2025-09-16 03:22:49"
    },
    {
      "text": "Is this joke wont you fact check it? Why this misleading headline",
      "timestamp": "2025-09-16 03:22:49"
    },
    {
      "text": "@pikaso_me\n screenshot this",
      "timestamp": "2025-09-16 03:22:49"
    },
    {
      "text": "@gupta_rekha\n कुछ भी ???",
      "timestamp": "2025-09-16 03:22:49"
    },
    {
      "text": "But English is enough, no need to learn that hardest Sanskrit.",
      "timestamp": "2025-09-16 03:22:49"
    },
    {
      "text": "कृपया संस्कृत को दिल्ली की आधिकारिक भाषा बनाएँ. सारे साइन बोर्ड संस्कृत में हों. ऑफिसों मे संस्कृत मे काम काज हो. आप भाषण भी संस्कृत मे दें",
      "timestamp": "2025-09-16 03:22:49"
    },
    {
      "text": "It’s old style of rss, I heard this in my school life from our principal h b Kapadia in the new high school Ahmedabad in 1990",
      "timestamp": "2025-09-16 03:22:49"
    },
    {
      "text": "@grok\n is this true ??",
      "timestamp": "2025-09-16 03:22:49"
    },
    {
      "text": "Bhai ye toh kuchh bhi nahi hai, NASA me coding bhi hoti hai.",
      "timestamp": "2025-09-16 03:22:49"
    },
    {
      "text": "Aiyaya... first, we had only Modi and his naali gas, but now we have a match..",
      "timestamp": "2025-09-16 03:22:49"
    },
    {
      "text": "WhatsApp university",
      "timestamp": "2025-09-16 03:22:49"
    },
    {
      "text": "@NASA\n \nPlease share  the information.",
      "timestamp": "2025-09-16 03:22:49"
    },
    {
      "text": "Whatsapp Forward and half baked knowldedge\nsearchsagechronical.blogspot.com/2024/04/decodi\n…",
      "timestamp": "2025-09-16 03:22:49"
    },
    {
      "text": "theek hai\n\nneta logon mein hodd lagi hai kaun kitna whatsapp gyan failaa sakta",
      "timestamp": "2025-09-16 03:23:20"
    },
    {
      "text": "Yeh Delhi ki cm h ",
      "timestamp": "2025-09-16 03:23:20"
    },
    {
      "text": "Science should be alive but don’t know why it’s dead",
      "timestamp": "2025-09-16 03:23:20"
    },
    {
      "text": " height of buffoonery",
      "timestamp": "2025-09-16 03:23:20"
    },
    {
      "text": "Lol... Delhites... The joke is on you",
      "timestamp": "2025-09-16 03:23:20"
    },
    {
      "text": "Proof of the pudding is in the eating",
      "timestamp": "2025-09-16 03:23:20"
    },
    {
      "text": "Though Groak denies it.",
      "timestamp": "2025-09-16 03:23:20"
    },
    {
      "text": "@NASA\n Hey NASA is this true ?",
      "timestamp": "2025-09-16 03:23:20"
    },
    {
      "text": "Delulu stuff from leaders is pretty common.",
      "timestamp": "2025-09-16 03:23:20"
    },
    {
      "text": "Public :: But no one has read those papers ever\nRekha Gupta :: because they are written in sanskrit by \" Nulla Ashikhit Samuhik Aakhada \"",
      "timestamp": "2025-09-16 03:23:20"
    },
    {
      "text": "Congratulations. Hope next time atleast give speech in sanskrit",
      "timestamp": "2025-09-16 03:23:20"
    },
    {
      "text": "Delhi's Literacy Rate in 5 years:",
      "timestamp": "2025-09-16 03:23:20"
    },
    {
      "text": "Epic...! Is she really CM of Delhi?? \n@ravishndtv\n @BBCHindi\n @dhruv_rathee\n ?",
      "timestamp": "2025-09-16 03:23:20"
    },
    {
      "text": "This is the level of joke that this woman is. Doom of the country, the people who have put her there.",
      "timestamp": "2025-09-16 03:23:20"
    },
    {
      "text": "Alice in wonderland...",
      "timestamp": "2025-09-16 03:23:20"
    },
    {
      "text": "@hariksBHIM",
      "timestamp": "2025-09-16 03:23:20"
    },
    {
      "text": "It seems god has gifted all clowns in India only.",
      "timestamp": "2025-09-16 03:23:20"
    },
    {
      "text": "Why country going backwards man its tuff",
      "timestamp": "2025-09-16 03:23:20"
    },
    {
      "text": "Relax Guys, Here NASA stands for National Association of Sanghi Â$$-Holes",
      "timestamp": "2025-09-16 03:23:20"
    },
    {
      "text": "Dear \n@Grok\n,\n\nWhat is the basis of such claims made by Delhi CM \n@gupta_rekha\n?\nx.com/the_hindu/stat\n…",
      "timestamp": "2025-09-16 03:23:20"
    },
    {
      "text": "Hey BJP, Beti padhaao.",
      "timestamp": "2025-09-16 03:23:20"
    },
    {
      "text": "What is NASA…it’s space x …someone need go get the speed on wats happening",
      "timestamp": "2025-09-16 03:23:20"
    },
    {
      "text": "@grok\n what’s the qualification of Delhi’s chief minister .",
      "timestamp": "2025-09-16 03:23:20"
    },
    {
      "text": "@NASA\n  did u ?",
      "timestamp": "2025-09-16 03:23:51"
    },
    {
      "text": "@grok\n just why are right wing politicians so silly and talk absurd gibberish all the time with no basis or logic ?",
      "timestamp": "2025-09-16 03:23:51"
    },
    {
      "text": "Hi \n@grok\n , could you please fact-check Rekha Gupta?",
      "timestamp": "2025-09-16 03:23:51"
    },
    {
      "text": "We know it is not true, still  how is that relevant to a common person of Delhi ?",
      "timestamp": "2025-09-16 03:23:51"
    },
    {
      "text": "@grok\n fact check if claim by Rekha gupta is right?",
      "timestamp": "2025-09-16 03:23:51"
    },
    {
      "text": "@grok\n can you validate this claim ?",
      "timestamp": "2025-09-16 03:23:51"
    },
    {
      "text": "@AskPerplexity\n is this correct?",
      "timestamp": "2025-09-16 03:23:51"
    },
    {
      "text": "Hey \n@grok\n \n\nIs it true?",
      "timestamp": "2025-09-16 03:23:51"
    },
    {
      "text": "@grok\n is this true?",
      "timestamp": "2025-09-16 03:23:51"
    },
    {
      "text": "@grok\n  is this true?",
      "timestamp": "2025-09-16 03:23:51"
    },
    {
      "text": "@grok\n fact check this",
      "timestamp": "2025-09-16 03:23:51"
    },
    {
      "text": "@grok\n did NASA write about Sanskrit?",
      "timestamp": "2025-09-16 03:23:51"
    },
    {
      "text": "Hello \n@grok\n \nWhy is sanskrit not a commoner’s language ?",
      "timestamp": "2025-09-16 03:23:51"
    },
    {
      "text": "@grok\n please verify these claims",
      "timestamp": "2025-09-16 03:23:51"
    },
    {
      "text": "@grok\n please debunk this",
      "timestamp": "2025-09-16 03:23:51"
    },
    {
      "text": "@NASA\n, please clarify all these claims. \n@grok\n  teri baat ye log mante hi nahi hai.",
      "timestamp": "2025-09-16 03:23:51"
    },
    {
      "text": "@grok\n क्या पोस्ट ने लिखी गई बाते सत्य है ?",
      "timestamp": "2025-09-16 03:23:51"
    },
    {
      "text": "@grok\n has NASA written papers on Sanskrit ?",
      "timestamp": "2025-09-16 03:23:51"
    },
    {
      "text": "@grok\n can you tell me more about NASA article on Sanskrit in AI (Artificial Intelligence) Magazine in Spring of 1985 written by NASA researcher, Rick Briggs.",
      "timestamp": "2025-09-16 03:23:51"
    },
    {
      "text": "@grok\n has NASA written a paper on Sanskrit being a scientific language?",
      "timestamp": "2025-09-16 03:23:51"
    },
    {
      "text": "@grok\n please fact check this",
      "timestamp": "2025-09-16 03:23:51"
    },
    {
      "text": "Hey \n@grok\n is this true ?",
      "timestamp": "2025-09-16 03:23:51"
    },
    {
      "text": "@grok\n IS IT TRUE?",
      "timestamp": "2025-09-16 03:23:51"
    },
    {
      "text": "@grok\n can u verify it?",
      "timestamp": "2025-09-16 03:23:51"
    },
    {
      "text": "@grok\n your view",
      "timestamp": "2025-09-16 03:23:51"
    },
    {
      "text": "@grok\n please verify the statement true or false",
      "timestamp": "2025-09-16 03:23:51"
    },
    {
      "text": "@grok\n \nIs this true?",
      "timestamp": "2025-09-16 03:23:51"
    },
    {
      "text": "What a bore... I know a fair amount of Sanskrit and have read the Valmiki Ramayana too in Sanskrit. Plus my mother is a Kovidha in Sanskrit. But this constant bragging and harping by Jumla group is extremely irritating to say the least.. look into the future.. ",
      "timestamp": "2025-09-16 03:23:51"
    },
    {
      "text": "@gupta_rekha\n lied.\n\nNot surprising!",
      "timestamp": "2025-09-16 03:23:51"
    },
    {
      "text": "Real coders after finding out what sanskrit is ",
      "timestamp": "2025-09-16 03:24:22"
    },
    {
      "text": "May be because Kamshastra was in #Sanskrit and she may be confused by studies of #Freud #Kinsley #AlanSoble as NASA studies.",
      "timestamp": "2025-09-16 03:24:22"
    },
    {
      "text": "India’s #1 university- WhatsApp university",
      "timestamp": "2025-09-16 03:24:22"
    },
    {
      "text": "Yeah ! Even the guys who know C++ is more than guys who use Sanskrit! A language of godsss who didn’t care preserving it ! Come on ! What a delusion !",
      "timestamp": "2025-09-16 03:24:22"
    },
    {
      "text": "From an IIT’an and IRS CM Kejriwal to this illiterate and dumb woman, Delhi fell from grace too low and too fast. So sad and disheartening to see.",
      "timestamp": "2025-09-16 03:24:22"
    },
    {
      "text": "On the contrary to your boasting history narrates the rulers of Delhi never had any strong weapon to face the challenging invaders, including Alexander the great, central Asian tribal leaders, the Mughals and the British.",
      "timestamp": "2025-09-16 03:24:22"
    },
    {
      "text": "In Germany, the study of ancient Indian scientific treatises written in Sanskrit has opened new avenues for academic exploration. These texts, spanning astronomy to medicine, are not treated as mere historical records but as repositories of knowledge with ongoing relevance to",
      "timestamp": "2025-09-16 03:24:22"
    },
    {
      "text": "We should use in our space technology ",
      "timestamp": "2025-09-16 03:24:22"
    },
    {
      "text": "Is bkl ko to NASA ka full form tak pata nahi hoga.. ",
      "timestamp": "2025-09-16 03:24:22"
    },
    {
      "text": "RIP delhi people....",
      "timestamp": "2025-09-16 03:24:22"
    },
    {
      "text": "@NASA\n can you please confirm this news. Need to switch from Python to Sanskrit asap.",
      "timestamp": "2025-09-16 03:24:22"
    },
    {
      "text": "Delhis ",
      "timestamp": "2025-09-16 03:24:22"
    },
    {
      "text": "Yet they are promoting urdu in schools. \nWhat a greed for votes! ",
      "timestamp": "2025-09-16 03:24:22"
    },
    {
      "text": "a political party that hinges on \"nationalism\" horseshit...always seeks western validation. Interesting stuff.",
      "timestamp": "2025-09-16 03:24:22"
    },
    {
      "text": "Jai, Modi ko  Maro ",
      "timestamp": "2025-09-16 03:24:22"
    },
    {
      "text": "@grok\n @AskPerplexity\n Did NASA really write papers on Sanskrit being a scientific language?",
      "timestamp": "2025-09-16 03:24:23"
    },
    {
      "text": "@grok\n: Has NASA written papers on Sanskrit being a scientific language?",
      "timestamp": "2025-09-16 03:24:23"
    },
    {
      "text": "Why are we so obsessed with outsider approval ??",
      "timestamp": "2025-09-16 03:25:58"
    },
    {
      "text": "Almost oblivious\nIn India",
      "timestamp": "2025-09-16 03:25:59"
    },
    {
      "text": "Sare bolo Jai Modu ki. Jor se bolo Jai Modu ki \n@nehafolksinger\n Arrey bhai hum par FIR na krwa dena kahin. Hum desh darohi nhi hai sahib ",
      "timestamp": "2025-09-16 03:25:59"
    },
    {
      "text": "wah! but ISRO didn’t. why you need validation from an international agency?",
      "timestamp": "2025-09-16 03:25:59"
    },
    {
      "text": "Inhe koi gyaan do bhai",
      "timestamp": "2025-09-16 03:25:59"
    },
    {
      "text": "Ye fir se fake news chalane lage...",
      "timestamp": "2025-09-16 03:25:59"
    },
    {
      "text": "not really",
      "timestamp": "2025-09-16 03:25:59"
    },
    {
      "text": "facts and logic committed suicide itself after listening to her speech ..",
      "timestamp": "2025-09-16 03:25:59"
    },
    {
      "text": "Jiss desh ka pradhan mantri hi nali ke gas se chai banata hi is desh ka yahi haal hoga.",
      "timestamp": "2025-09-16 03:25:59"
    },
    {
      "text": "Sanskrit is a dead and useless language.",
      "timestamp": "2025-09-16 03:25:59"
    },
    {
      "text": "Delhites chose her, so keep suffering",
      "timestamp": "2025-09-16 03:25:59"
    },
    {
      "text": "Whatsapp CM .",
      "timestamp": "2025-09-16 03:25:59"
    },
    {
      "text": "Saintifik language s44r",
      "timestamp": "2025-09-16 03:25:59"
    },
    {
      "text": "@grok\n can you confirm claim if Sanskrit is NASA has written paper on it",
      "timestamp": "2025-09-16 03:25:59"
    },
    {
      "text": "@grok\n ,please fact check",
      "timestamp": "2025-09-16 03:26:49"
    }
  ],
  "metadata": {
    "last_scroll_position": 58893,
    "last_save_time": "2025-09-16 03:29:48",
    "raw_comment_count": 236
  }
}