{
  "channel_name": "ProjectShivoham",
  "conversation_id": "1948216995075268785",
  "url": "https://x.com/ProjectShivoham/status/1948216995075268785",
  "total_comments": 2,
  "scrape_start_time": "2025-09-17 20:27:47",
  "comments": {
    "post": {
      "text": "Language Chauvinism (extreme disrespect towards other state languages) is a Colonial divide that was first introduced into India by British in Tamil Nadu…\n\nThis mindset has now crept into Karnataka and Maharashtra… \n\nAs a Telugu native person, I am proud that we never hate any OTHER state’s language… that’s because we are busy hating our OWN language Telugu… hence Andhra-Telangana split happed… \n\nThe linguistic landscape of India is one hell of a squid game where all of us are set to lose fighting each other…",
      "user_name": "Project SHIVOHAM",
      "user_handle": null,
      "post_time": "2025-07-24T03:01:42.000Z",
      "scrape_time": "2025-09-17 20:27:18"
    },
    "comments": [
      {
        "text": "Language Chauvinism (extreme disrespect towards other state languages) is a Colonial divide that was first introduced into India by British in Tamil Nadu…\n\nThis mindset has now crept into Karnataka and Maharashtra… \n\nAs a Telugu native person, I am proud that we never hate any OTHER state’s language… that’s because we are busy hating our OWN language Telugu… hence Andhra-Telangana split happed… \n\nThe linguistic landscape of India is one hell of a squid game where all of us are set to lose fighting each other…",
        "user_name": "Project SHIVOHAM",
        "user_handle": null,
        "comment_time": "2025-07-24T03:01:42.000Z",
        "scrape_time": "2025-09-17 20:27:18"
      },
      {
        "text": "> The linguistic landscape of India is one hell of a squid game where all of us are set to lose fighting each other… \n\nSo true.",
        "user_name": "Jagan Mohan",
        "user_handle": null,
        "comment_time": "2025-07-24T04:16:15.000Z",
        "scrape_time": "2025-09-17 20:27:18"
      },
      {
        "text": "That mindset is spread now by congress they  get minority votes and they want to divide Hindus by caste language and get a part of that vote bank",
        "user_name": "ramkumaran",
        "user_handle": null,
        "comment_time": "2025-07-24T03:24:21.000Z",
        "scrape_time": "2025-09-17 20:27:18"
      },
      {
        "text": "The disrespect to the state language is shown by people going to that state ,not learning local ,no assimilation ,showing arrogance n attitude to local as if they did some favour on state . Once they start assimilation to local culture ,all this will stop..",
        "user_name": "Anaamika",
        "user_handle": null,
        "comment_time": "2025-07-24T05:10:32.000Z",
        "scrape_time": "2025-09-17 20:27:18"
      },
      {
        "text": "India is a country of unity in diversity where evry state has a different language,culture,tradition, all stemming frm the same root. Therefore evry1 should be loyal 2 their land, language. I don't think there's anything wrng with defending ur language. U defend Sanskrit dont u?",
        "user_name": "Valluvar The Great",
        "user_handle": null,
        "comment_time": "2025-07-24T03:58:05.000Z",
        "scrape_time": "2025-09-17 20:27:18"
      },
      {
        "text": "Agree with everything short of calling Hindi \"the National language\". We already have enough \"you don't know Hindi, how are you in India\" types\nTalk any language you like, don't even need to learn the local language if it is not giving you anything back",
        "user_name": "Vamsi",
        "user_handle": null,
        "comment_time": "2025-07-24T03:56:17.000Z",
        "scrape_time": "2025-09-17 20:27:18"
      },
      {
        "text": "Learning a new language is a tough process for most. It is your right to ask \"what will I get from it\" before you learn it\nI can also stay at a place for 10+ yrs and not learn the language if I don't get right answer\nDon't go to a new place and demand they speak your language x.com/NAYAKBHAIII/st…",
        "user_name": "Vamsi",
        "user_handle": null,
        "comment_time": "2025-07-20T14:08:56.000Z",
        "scrape_time": "2025-09-17 20:27:18"
      },
      {
        "text": "Same goes to Haryana. Anyone and everyone is welcome here. Respect all cultures and languages.",
        "user_name": "RetroPicture",
        "user_handle": null,
        "comment_time": "2025-07-24T06:17:49.000Z",
        "scrape_time": "2025-09-17 20:27:18"
      },
      {
        "text": "I really don't understand how can you have language chauvinism... I am  tamilian and I have no hate towards any indian languages ... How can you hate any indian languages ?",
        "user_name": "CivilizationalWarrior",
        "user_handle": null,
        "comment_time": "2025-07-24T03:51:15.000Z",
        "scrape_time": "2025-09-17 20:27:18"
      },
      {
        "text": "You should calm down ,\nDon't Talk much about it...\nThe Day Congress starts funding Telugu Activism , it's over for you ",
        "user_name": "Amar",
        "user_handle": null,
        "comment_time": "2025-07-24T04:20:12.000Z",
        "scrape_time": "2025-09-17 20:27:19"
      },
      {
        "text": "A politician says our language is unity in diversity . Multilingual states must be promoted if at all some futuristic hypothetical leader emerge in Bharata.",
        "user_name": "rahogata",
        "user_handle": null,
        "comment_time": "2025-07-25T12:36:07.000Z",
        "scrape_time": "2025-09-17 20:27:19"
      },
      {
        "text": "Language Chauvinism (extreme disrespect towards other state languages) is a Colonial divide that was first introduced into India by British in Tamil Nadu…\n\nThis mindset has now crept into Karnataka and Maharashtra… \n\nAs a Telugu native person, I am proud that we never hate any OTHER state’s language… that’s because we are busy hating our OWN language Telugu… hence Andhra-Telangana split happed… \n\nThe linguistic landscape of India is one hell of a squid game where all of us are set to lose fighting each other…",
        "user_name": "Project SHIVOHAM",
        "user_handle": null,
        "comment_time": "2025-07-24T03:01:42.000Z",
        "scrape_time": "2025-09-17 20:27:19"
      },
      {
        "text": "> The linguistic landscape of India is one hell of a squid game where all of us are set to lose fighting each other… \n\nSo true.",
        "user_name": "Jagan Mohan",
        "user_handle": null,
        "comment_time": "2025-07-24T04:16:15.000Z",
        "scrape_time": "2025-09-17 20:27:19"
      },
      {
        "text": "That mindset is spread now by congress they  get minority votes and they want to divide Hindus by caste language and get a part of that vote bank",
        "user_name": "ramkumaran",
        "user_handle": null,
        "comment_time": "2025-07-24T03:24:21.000Z",
        "scrape_time": "2025-09-17 20:27:19"
      },
      {
        "text": "The disrespect to the state language is shown by people going to that state ,not learning local ,no assimilation ,showing arrogance n attitude to local as if they did some favour on state . Once they start assimilation to local culture ,all this will stop..",
        "user_name": "Anaamika",
        "user_handle": null,
        "comment_time": "2025-07-24T05:10:32.000Z",
        "scrape_time": "2025-09-17 20:27:19"
      },
      {
        "text": "India is a country of unity in diversity where evry state has a different language,culture,tradition, all stemming frm the same root. Therefore evry1 should be loyal 2 their land, language. I don't think there's anything wrng with defending ur language. U defend Sanskrit dont u?",
        "user_name": "Valluvar The Great",
        "user_handle": null,
        "comment_time": "2025-07-24T03:58:05.000Z",
        "scrape_time": "2025-09-17 20:27:19"
      },
      {
        "text": "Agree with everything short of calling Hindi \"the National language\". We already have enough \"you don't know Hindi, how are you in India\" types\nTalk any language you like, don't even need to learn the local language if it is not giving you anything back",
        "user_name": "Vamsi",
        "user_handle": null,
        "comment_time": "2025-07-24T03:56:17.000Z",
        "scrape_time": "2025-09-17 20:27:19"
      },
      {
        "text": "Learning a new language is a tough process for most. It is your right to ask \"what will I get from it\" before you learn it\nI can also stay at a place for 10+ yrs and not learn the language if I don't get right answer\nDon't go to a new place and demand they speak your language x.com/NAYAKBHAIII/st…",
        "user_name": "Vamsi",
        "user_handle": null,
        "comment_time": "2025-07-20T14:08:56.000Z",
        "scrape_time": "2025-09-17 20:27:19"
      },
      {
        "text": "Same goes to Haryana. Anyone and everyone is welcome here. Respect all cultures and languages.",
        "user_name": "RetroPicture",
        "user_handle": null,
        "comment_time": "2025-07-24T06:17:49.000Z",
        "scrape_time": "2025-09-17 20:27:19"
      },
      {
        "text": "I really don't understand how can you have language chauvinism... I am  tamilian and I have no hate towards any indian languages ... How can you hate any indian languages ?",
        "user_name": "CivilizationalWarrior",
        "user_handle": null,
        "comment_time": "2025-07-24T03:51:15.000Z",
        "scrape_time": "2025-09-17 20:27:19"
      },
      {
        "text": "",
        "user_name": "भारतFIRST",
        "user_handle": null,
        "comment_time": "2025-07-24T04:22:05.000Z",
        "scrape_time": "2025-09-17 20:27:19"
      },
      {
        "text": "You should calm down ,\nDon't Talk much about it...\nThe Day Congress starts funding Telugu Activism , it's over for you ",
        "user_name": "Amar",
        "user_handle": null,
        "comment_time": "2025-07-24T04:20:12.000Z",
        "scrape_time": "2025-09-17 20:27:19"
      },
      {
        "text": "A politician says our language is unity in diversity . Multilingual states must be promoted if at all some futuristic hypothetical leader emerge in Bharata.",
        "user_name": "rahogata",
        "user_handle": null,
        "comment_time": "2025-07-25T12:36:07.000Z",
        "scrape_time": "2025-09-17 20:27:19"
      },
      {
        "text": "Language Chauvinism (extreme disrespect towards other state languages) is a Colonial divide that was first introduced into India by British in Tamil Nadu…\n\nThis mindset has now crept into Karnataka and Maharashtra… \n\nAs a Telugu native person, I am proud that we never hate any OTHER state’s language… that’s because we are busy hating our OWN language Telugu… hence Andhra-Telangana split happed… \n\nThe linguistic landscape of India is one hell of a squid game where all of us are set to lose fighting each other…",
        "user_name": "Project SHIVOHAM",
        "user_handle": null,
        "comment_time": "2025-07-24T03:01:42.000Z",
        "scrape_time": "2025-09-17 20:27:27"
      },
      {
        "text": "> The linguistic landscape of India is one hell of a squid game where all of us are set to lose fighting each other… \n\nSo true.",
        "user_name": "Jagan Mohan",
        "user_handle": null,
        "comment_time": "2025-07-24T04:16:15.000Z",
        "scrape_time": "2025-09-17 20:27:27"
      },
      {
        "text": "That mindset is spread now by congress they  get minority votes and they want to divide Hindus by caste language and get a part of that vote bank",
        "user_name": "ramkumaran",
        "user_handle": null,
        "comment_time": "2025-07-24T03:24:21.000Z",
        "scrape_time": "2025-09-17 20:27:27"
      },
      {
        "text": "The disrespect to the state language is shown by people going to that state ,not learning local ,no assimilation ,showing arrogance n attitude to local as if they did some favour on state . Once they start assimilation to local culture ,all this will stop..",
        "user_name": "Anaamika",
        "user_handle": null,
        "comment_time": "2025-07-24T05:10:32.000Z",
        "scrape_time": "2025-09-17 20:27:28"
      },
      {
        "text": "India is a country of unity in diversity where evry state has a different language,culture,tradition, all stemming frm the same root. Therefore evry1 should be loyal 2 their land, language. I don't think there's anything wrng with defending ur language. U defend Sanskrit dont u?",
        "user_name": "Valluvar The Great",
        "user_handle": null,
        "comment_time": "2025-07-24T03:58:05.000Z",
        "scrape_time": "2025-09-17 20:27:28"
      },
      {
        "text": "Agree with everything short of calling Hindi \"the National language\". We already have enough \"you don't know Hindi, how are you in India\" types\nTalk any language you like, don't even need to learn the local language if it is not giving you anything back",
        "user_name": "Vamsi",
        "user_handle": null,
        "comment_time": "2025-07-24T03:56:17.000Z",
        "scrape_time": "2025-09-17 20:27:28"
      },
      {
        "text": "Learning a new language is a tough process for most. It is your right to ask \"what will I get from it\" before you learn it\nI can also stay at a place for 10+ yrs and not learn the language if I don't get right answer\nDon't go to a new place and demand they speak your language x.com/NAYAKBHAIII/st…",
        "user_name": "Vamsi",
        "user_handle": null,
        "comment_time": "2025-07-20T14:08:56.000Z",
        "scrape_time": "2025-09-17 20:27:28"
      },
      {
        "text": "Same goes to Haryana. Anyone and everyone is welcome here. Respect all cultures and languages.",
        "user_name": "RetroPicture",
        "user_handle": null,
        "comment_time": "2025-07-24T06:17:49.000Z",
        "scrape_time": "2025-09-17 20:27:28"
      },
      {
        "text": "I really don't understand how can you have language chauvinism... I am  tamilian and I have no hate towards any indian languages ... How can you hate any indian languages ?",
        "user_name": "CivilizationalWarrior",
        "user_handle": null,
        "comment_time": "2025-07-24T03:51:15.000Z",
        "scrape_time": "2025-09-17 20:27:28"
      },
      {
        "text": "",
        "user_name": "भारतFIRST",
        "user_handle": null,
        "comment_time": "2025-07-24T04:22:05.000Z",
        "scrape_time": "2025-09-17 20:27:28"
      },
      {
        "text": "You should calm down ,\nDon't Talk much about it...\nThe Day Congress starts funding Telugu Activism , it's over for you ",
        "user_name": "Amar",
        "user_handle": null,
        "comment_time": "2025-07-24T04:20:12.000Z",
        "scrape_time": "2025-09-17 20:27:28"
      },
      {
        "text": "A politician says our language is unity in diversity . Multilingual states must be promoted if at all some futuristic hypothetical leader emerge in Bharata.",
        "user_name": "rahogata",
        "user_handle": null,
        "comment_time": "2025-07-25T12:36:07.000Z",
        "scrape_time": "2025-09-17 20:27:28"
      },
      {
        "text": "Language Chauvinism (extreme disrespect towards other state languages) is a Colonial divide that was first introduced into India by British in Tamil Nadu…\n\nThis mindset has now crept into Karnataka and Maharashtra… \n\nAs a Telugu native person, I am proud that we never hate any OTHER state’s language… that’s because we are busy hating our OWN language Telugu… hence Andhra-Telangana split happed… \n\nThe linguistic landscape of India is one hell of a squid game where all of us are set to lose fighting each other…",
        "user_name": "Project SHIVOHAM",
        "user_handle": null,
        "comment_time": "2025-07-24T03:01:42.000Z",
        "scrape_time": "2025-09-17 20:27:28"
      },
      {
        "text": "> The linguistic landscape of India is one hell of a squid game where all of us are set to lose fighting each other… \n\nSo true.",
        "user_name": "Jagan Mohan",
        "user_handle": null,
        "comment_time": "2025-07-24T04:16:15.000Z",
        "scrape_time": "2025-09-17 20:27:28"
      },
      {
        "text": "That mindset is spread now by congress they  get minority votes and they want to divide Hindus by caste language and get a part of that vote bank",
        "user_name": "ramkumaran",
        "user_handle": null,
        "comment_time": "2025-07-24T03:24:21.000Z",
        "scrape_time": "2025-09-17 20:27:28"
      },
      {
        "text": "The disrespect to the state language is shown by people going to that state ,not learning local ,no assimilation ,showing arrogance n attitude to local as if they did some favour on state . Once they start assimilation to local culture ,all this will stop..",
        "user_name": "Anaamika",
        "user_handle": null,
        "comment_time": "2025-07-24T05:10:32.000Z",
        "scrape_time": "2025-09-17 20:27:28"
      },
      {
        "text": "India is a country of unity in diversity where evry state has a different language,culture,tradition, all stemming frm the same root. Therefore evry1 should be loyal 2 their land, language. I don't think there's anything wrng with defending ur language. U defend Sanskrit dont u?",
        "user_name": "Valluvar The Great",
        "user_handle": null,
        "comment_time": "2025-07-24T03:58:05.000Z",
        "scrape_time": "2025-09-17 20:27:28"
      },
      {
        "text": "Agree with everything short of calling Hindi \"the National language\". We already have enough \"you don't know Hindi, how are you in India\" types\nTalk any language you like, don't even need to learn the local language if it is not giving you anything back",
        "user_name": "Vamsi",
        "user_handle": null,
        "comment_time": "2025-07-24T03:56:17.000Z",
        "scrape_time": "2025-09-17 20:27:28"
      },
      {
        "text": "Learning a new language is a tough process for most. It is your right to ask \"what will I get from it\" before you learn it\nI can also stay at a place for 10+ yrs and not learn the language if I don't get right answer\nDon't go to a new place and demand they speak your language x.com/NAYAKBHAIII/st…",
        "user_name": "Vamsi",
        "user_handle": null,
        "comment_time": "2025-07-20T14:08:56.000Z",
        "scrape_time": "2025-09-17 20:27:28"
      },
      {
        "text": "Same goes to Haryana. Anyone and everyone is welcome here. Respect all cultures and languages.",
        "user_name": "RetroPicture",
        "user_handle": null,
        "comment_time": "2025-07-24T06:17:49.000Z",
        "scrape_time": "2025-09-17 20:27:28"
      },
      {
        "text": "I really don't understand how can you have language chauvinism... I am  tamilian and I have no hate towards any indian languages ... How can you hate any indian languages ?",
        "user_name": "CivilizationalWarrior",
        "user_handle": null,
        "comment_time": "2025-07-24T03:51:15.000Z",
        "scrape_time": "2025-09-17 20:27:29"
      },
      {
        "text": "",
        "user_name": "भारतFIRST",
        "user_handle": null,
        "comment_time": "2025-07-24T04:22:05.000Z",
        "scrape_time": "2025-09-17 20:27:29"
      },
      {
        "text": "You should calm down ,\nDon't Talk much about it...\nThe Day Congress starts funding Telugu Activism , it's over for you ",
        "user_name": "Amar",
        "user_handle": null,
        "comment_time": "2025-07-24T04:20:12.000Z",
        "scrape_time": "2025-09-17 20:27:29"
      },
      {
        "text": "A politician says our language is unity in diversity . Multilingual states must be promoted if at all some futuristic hypothetical leader emerge in Bharata.",
        "user_name": "rahogata",
        "user_handle": null,
        "comment_time": "2025-07-25T12:36:07.000Z",
        "scrape_time": "2025-09-17 20:27:29"
      },
      {
        "text": "Language Chauvinism (extreme disrespect towards other state languages) is a Colonial divide that was first introduced into India by British in Tamil Nadu…\n\nThis mindset has now crept into Karnataka and Maharashtra… \n\nAs a Telugu native person, I am proud that we never hate any OTHER state’s language… that’s because we are busy hating our OWN language Telugu… hence Andhra-Telangana split happed… \n\nThe linguistic landscape of India is one hell of a squid game where all of us are set to lose fighting each other…",
        "user_name": "Project SHIVOHAM",
        "user_handle": null,
        "comment_time": "2025-07-24T03:01:42.000Z",
        "scrape_time": "2025-09-17 20:27:37"
      },
      {
        "text": "> The linguistic landscape of India is one hell of a squid game where all of us are set to lose fighting each other… \n\nSo true.",
        "user_name": "Jagan Mohan",
        "user_handle": null,
        "comment_time": "2025-07-24T04:16:15.000Z",
        "scrape_time": "2025-09-17 20:27:37"
      },
      {
        "text": "That mindset is spread now by congress they  get minority votes and they want to divide Hindus by caste language and get a part of that vote bank",
        "user_name": "ramkumaran",
        "user_handle": null,
        "comment_time": "2025-07-24T03:24:21.000Z",
        "scrape_time": "2025-09-17 20:27:37"
      },
      {
        "text": "The disrespect to the state language is shown by people going to that state ,not learning local ,no assimilation ,showing arrogance n attitude to local as if they did some favour on state . Once they start assimilation to local culture ,all this will stop..",
        "user_name": "Anaamika",
        "user_handle": null,
        "comment_time": "2025-07-24T05:10:32.000Z",
        "scrape_time": "2025-09-17 20:27:37"
      },
      {
        "text": "India is a country of unity in diversity where evry state has a different language,culture,tradition, all stemming frm the same root. Therefore evry1 should be loyal 2 their land, language. I don't think there's anything wrng with defending ur language. U defend Sanskrit dont u?",
        "user_name": "Valluvar The Great",
        "user_handle": null,
        "comment_time": "2025-07-24T03:58:05.000Z",
        "scrape_time": "2025-09-17 20:27:37"
      },
      {
        "text": "Agree with everything short of calling Hindi \"the National language\". We already have enough \"you don't know Hindi, how are you in India\" types\nTalk any language you like, don't even need to learn the local language if it is not giving you anything back",
        "user_name": "Vamsi",
        "user_handle": null,
        "comment_time": "2025-07-24T03:56:17.000Z",
        "scrape_time": "2025-09-17 20:27:37"
      },
      {
        "text": "Learning a new language is a tough process for most. It is your right to ask \"what will I get from it\" before you learn it\nI can also stay at a place for 10+ yrs and not learn the language if I don't get right answer\nDon't go to a new place and demand they speak your language x.com/NAYAKBHAIII/st…",
        "user_name": "Vamsi",
        "user_handle": null,
        "comment_time": "2025-07-20T14:08:56.000Z",
        "scrape_time": "2025-09-17 20:27:37"
      },
      {
        "text": "Same goes to Haryana. Anyone and everyone is welcome here. Respect all cultures and languages.",
        "user_name": "RetroPicture",
        "user_handle": null,
        "comment_time": "2025-07-24T06:17:49.000Z",
        "scrape_time": "2025-09-17 20:27:37"
      },
      {
        "text": "I really don't understand how can you have language chauvinism... I am  tamilian and I have no hate towards any indian languages ... How can you hate any indian languages ?",
        "user_name": "CivilizationalWarrior",
        "user_handle": null,
        "comment_time": "2025-07-24T03:51:15.000Z",
        "scrape_time": "2025-09-17 20:27:37"
      },
      {
        "text": "",
        "user_name": "भारतFIRST",
        "user_handle": null,
        "comment_time": "2025-07-24T04:22:05.000Z",
        "scrape_time": "2025-09-17 20:27:37"
      },
      {
        "text": "You should calm down ,\nDon't Talk much about it...\nThe Day Congress starts funding Telugu Activism , it's over for you ",
        "user_name": "Amar",
        "user_handle": null,
        "comment_time": "2025-07-24T04:20:12.000Z",
        "scrape_time": "2025-09-17 20:27:37"
      },
      {
        "text": "A politician says our language is unity in diversity . Multilingual states must be promoted if at all some futuristic hypothetical leader emerge in Bharata.",
        "user_name": "rahogata",
        "user_handle": null,
        "comment_time": "2025-07-25T12:36:07.000Z",
        "scrape_time": "2025-09-17 20:27:37"
      },
      {
        "text": "Language Chauvinism (extreme disrespect towards other state languages) is a Colonial divide that was first introduced into India by British in Tamil Nadu…\n\nThis mindset has now crept into Karnataka and Maharashtra… \n\nAs a Telugu native person, I am proud that we never hate any OTHER state’s language… that’s because we are busy hating our OWN language Telugu… hence Andhra-Telangana split happed… \n\nThe linguistic landscape of India is one hell of a squid game where all of us are set to lose fighting each other…",
        "user_name": "Project SHIVOHAM",
        "user_handle": null,
        "comment_time": "2025-07-24T03:01:42.000Z",
        "scrape_time": "2025-09-17 20:27:37"
      },
      {
        "text": "> The linguistic landscape of India is one hell of a squid game where all of us are set to lose fighting each other… \n\nSo true.",
        "user_name": "Jagan Mohan",
        "user_handle": null,
        "comment_time": "2025-07-24T04:16:15.000Z",
        "scrape_time": "2025-09-17 20:27:38"
      },
      {
        "text": "That mindset is spread now by congress they  get minority votes and they want to divide Hindus by caste language and get a part of that vote bank",
        "user_name": "ramkumaran",
        "user_handle": null,
        "comment_time": "2025-07-24T03:24:21.000Z",
        "scrape_time": "2025-09-17 20:27:38"
      },
      {
        "text": "The disrespect to the state language is shown by people going to that state ,not learning local ,no assimilation ,showing arrogance n attitude to local as if they did some favour on state . Once they start assimilation to local culture ,all this will stop..",
        "user_name": "Anaamika",
        "user_handle": null,
        "comment_time": "2025-07-24T05:10:32.000Z",
        "scrape_time": "2025-09-17 20:27:38"
      },
      {
        "text": "India is a country of unity in diversity where evry state has a different language,culture,tradition, all stemming frm the same root. Therefore evry1 should be loyal 2 their land, language. I don't think there's anything wrng with defending ur language. U defend Sanskrit dont u?",
        "user_name": "Valluvar The Great",
        "user_handle": null,
        "comment_time": "2025-07-24T03:58:05.000Z",
        "scrape_time": "2025-09-17 20:27:38"
      },
      {
        "text": "Agree with everything short of calling Hindi \"the National language\". We already have enough \"you don't know Hindi, how are you in India\" types\nTalk any language you like, don't even need to learn the local language if it is not giving you anything back",
        "user_name": "Vamsi",
        "user_handle": null,
        "comment_time": "2025-07-24T03:56:17.000Z",
        "scrape_time": "2025-09-17 20:27:38"
      },
      {
        "text": "Learning a new language is a tough process for most. It is your right to ask \"what will I get from it\" before you learn it\nI can also stay at a place for 10+ yrs and not learn the language if I don't get right answer\nDon't go to a new place and demand they speak your language x.com/NAYAKBHAIII/st…",
        "user_name": "Vamsi",
        "user_handle": null,
        "comment_time": "2025-07-20T14:08:56.000Z",
        "scrape_time": "2025-09-17 20:27:38"
      },
      {
        "text": "Same goes to Haryana. Anyone and everyone is welcome here. Respect all cultures and languages.",
        "user_name": "RetroPicture",
        "user_handle": null,
        "comment_time": "2025-07-24T06:17:49.000Z",
        "scrape_time": "2025-09-17 20:27:38"
      },
      {
        "text": "I really don't understand how can you have language chauvinism... I am  tamilian and I have no hate towards any indian languages ... How can you hate any indian languages ?",
        "user_name": "CivilizationalWarrior",
        "user_handle": null,
        "comment_time": "2025-07-24T03:51:15.000Z",
        "scrape_time": "2025-09-17 20:27:38"
      },
      {
        "text": "",
        "user_name": "भारतFIRST",
        "user_handle": null,
        "comment_time": "2025-07-24T04:22:05.000Z",
        "scrape_time": "2025-09-17 20:27:38"
      },
      {
        "text": "You should calm down ,\nDon't Talk much about it...\nThe Day Congress starts funding Telugu Activism , it's over for you ",
        "user_name": "Amar",
        "user_handle": null,
        "comment_time": "2025-07-24T04:20:12.000Z",
        "scrape_time": "2025-09-17 20:27:38"
      },
      {
        "text": "A politician says our language is unity in diversity . Multilingual states must be promoted if at all some futuristic hypothetical leader emerge in Bharata.",
        "user_name": "rahogata",
        "user_handle": null,
        "comment_time": "2025-07-25T12:36:07.000Z",
        "scrape_time": "2025-09-17 20:27:38"
      },
      {
        "text": "Language Chauvinism (extreme disrespect towards other state languages) is a Colonial divide that was first introduced into India by British in Tamil Nadu…\n\nThis mindset has now crept into Karnataka and Maharashtra… \n\nAs a Telugu native person, I am proud that we never hate any OTHER state’s language… that’s because we are busy hating our OWN language Telugu… hence Andhra-Telangana split happed… \n\nThe linguistic landscape of India is one hell of a squid game where all of us are set to lose fighting each other…",
        "user_name": "Project SHIVOHAM",
        "user_handle": null,
        "comment_time": "2025-07-24T03:01:42.000Z",
        "scrape_time": "2025-09-17 20:27:46"
      },
      {
        "text": "> The linguistic landscape of India is one hell of a squid game where all of us are set to lose fighting each other… \n\nSo true.",
        "user_name": "Jagan Mohan",
        "user_handle": null,
        "comment_time": "2025-07-24T04:16:15.000Z",
        "scrape_time": "2025-09-17 20:27:46"
      },
      {
        "text": "That mindset is spread now by congress they  get minority votes and they want to divide Hindus by caste language and get a part of that vote bank",
        "user_name": "ramkumaran",
        "user_handle": null,
        "comment_time": "2025-07-24T03:24:21.000Z",
        "scrape_time": "2025-09-17 20:27:46"
      },
      {
        "text": "The disrespect to the state language is shown by people going to that state ,not learning local ,no assimilation ,showing arrogance n attitude to local as if they did some favour on state . Once they start assimilation to local culture ,all this will stop..",
        "user_name": "Anaamika",
        "user_handle": null,
        "comment_time": "2025-07-24T05:10:32.000Z",
        "scrape_time": "2025-09-17 20:27:46"
      },
      {
        "text": "India is a country of unity in diversity where evry state has a different language,culture,tradition, all stemming frm the same root. Therefore evry1 should be loyal 2 their land, language. I don't think there's anything wrng with defending ur language. U defend Sanskrit dont u?",
        "user_name": "Valluvar The Great",
        "user_handle": null,
        "comment_time": "2025-07-24T03:58:05.000Z",
        "scrape_time": "2025-09-17 20:27:46"
      },
      {
        "text": "Agree with everything short of calling Hindi \"the National language\". We already have enough \"you don't know Hindi, how are you in India\" types\nTalk any language you like, don't even need to learn the local language if it is not giving you anything back",
        "user_name": "Vamsi",
        "user_handle": null,
        "comment_time": "2025-07-24T03:56:17.000Z",
        "scrape_time": "2025-09-17 20:27:47"
      },
      {
        "text": "Learning a new language is a tough process for most. It is your right to ask \"what will I get from it\" before you learn it\nI can also stay at a place for 10+ yrs and not learn the language if I don't get right answer\nDon't go to a new place and demand they speak your language x.com/NAYAKBHAIII/st…",
        "user_name": "Vamsi",
        "user_handle": null,
        "comment_time": "2025-07-20T14:08:56.000Z",
        "scrape_time": "2025-09-17 20:27:47"
      },
      {
        "text": "Same goes to Haryana. Anyone and everyone is welcome here. Respect all cultures and languages.",
        "user_name": "RetroPicture",
        "user_handle": null,
        "comment_time": "2025-07-24T06:17:49.000Z",
        "scrape_time": "2025-09-17 20:27:47"
      },
      {
        "text": "I really don't understand how can you have language chauvinism... I am  tamilian and I have no hate towards any indian languages ... How can you hate any indian languages ?",
        "user_name": "CivilizationalWarrior",
        "user_handle": null,
        "comment_time": "2025-07-24T03:51:15.000Z",
        "scrape_time": "2025-09-17 20:27:47"
      },
      {
        "text": "",
        "user_name": "भारतFIRST",
        "user_handle": null,
        "comment_time": "2025-07-24T04:22:05.000Z",
        "scrape_time": "2025-09-17 20:27:47"
      },
      {
        "text": "You should calm down ,\nDon't Talk much about it...\nThe Day Congress starts funding Telugu Activism , it's over for you ",
        "user_name": "Amar",
        "user_handle": null,
        "comment_time": "2025-07-24T04:20:12.000Z",
        "scrape_time": "2025-09-17 20:27:47"
      },
      {
        "text": "A politician says our language is unity in diversity . Multilingual states must be promoted if at all some futuristic hypothetical leader emerge in Bharata.",
        "user_name": "rahogata",
        "user_handle": null,
        "comment_time": "2025-07-25T12:36:07.000Z",
        "scrape_time": "2025-09-17 20:27:47"
      }
    ]
  },
  "metadata": {
    "last_scroll_position": 2703,
    "last_save_time": "2025-09-17 20:27:47",
    "raw_comment_count": 2
  }
}